__init__.py
app.py
dane_gov_pl_mcp-0.1.0.dist-info/licenses/LICENSE
prompts/__init__.py
prompts/prompts.py
tools/__init__.py
tools/datasets.py
tools/institutions.py
tools/parsers.py
tools/resources.py
tools/showcases.py
tools/tabular.py
tools/utils.py
utils/__init__.py
utils/server_config.py
utils/update_categories.py
dane_gov_pl_mcp-0.1.0.dist-info/METADATA
dane_gov_pl_mcp-0.1.0.dist-info/WHEEL
dane_gov_pl_mcp-0.1.0.dist-info/top_level.txt
dane_gov_pl_mcp-0.1.0.dist-info/RECORD
