Metadata-Version: 2.4
Name: dane-gov-pl-mcp
Version: 0.1.0
Summary: MCP server for dane.gov.pl API
Requires-Python: >=3.11
License-File: LICENSE
Requires-Dist: async-lru>=2.0.5
Requires-Dist: fastexcel>=0.11.0
Requires-Dist: fastmcp>=2.10.2
Requires-Dist: polars>=1.31.0
Requires-Dist: unstructured[all-docs]>=0.18.9
Dynamic: license-file
